lv_chordia/__init__.py
lv_chordia/audio_utils.py
lv_chordia/chord_recognition.py
lv_chordia/chordnet_ismir_naive.py
lv_chordia/chordnet_ismir_naive_eval.py
lv_chordia/cli.py
lv_chordia/complex_chord.py
lv_chordia/datasets.py
lv_chordia/results.py
lv_chordia/results_ismir2017.py
lv_chordia/settings.py
lv_chordia/storage_creation.py
lv_chordia/test_for_all.py
lv_chordia/train_eval_test_split.py
lv_chordia/data/all_1217.csv
lv_chordia/data/chord_placeholder.lab
lv_chordia/data/chordino.n3
lv_chordia/data/complex_chord_structure.xlsx
lv_chordia/data/cross_subpart_weight0.pkl
lv_chordia/data/cross_subpart_weight1.pkl
lv_chordia/data/cross_subpart_weight2.pkl
lv_chordia/data/cross_subpart_weight3.pkl
lv_chordia/data/cross_subpart_weight4.pkl
lv_chordia/data/cross_weight0.pkl
lv_chordia/data/cross_weight1.pkl
lv_chordia/data/cross_weight2.pkl
lv_chordia/data/cross_weight3.pkl
lv_chordia/data/cross_weight4.pkl
lv_chordia/data/extended_chord_list.txt
lv_chordia/data/full_chord_list.txt
lv_chordia/data/ismir2017_chord_list.txt
lv_chordia/data/midi_template.svl
lv_chordia/data/submission_chord_list.txt
lv_chordia/data/test00.csv
lv_chordia/data/test01.csv
lv_chordia/data/test02.csv
lv_chordia/data/test03.csv
lv_chordia/data/test04.csv
lv_chordia/data/train00.csv
lv_chordia/data/train01.csv
lv_chordia/data/train02.csv
lv_chordia/data/train03.csv
lv_chordia/data/train04.csv
lv_chordia/extractors/__init__.py
lv_chordia/extractors/beat_preprocess.py
lv_chordia/extractors/beat_preprocess_legacy.py
lv_chordia/extractors/chord_name_fix.py
lv_chordia/extractors/chord_shift.py
lv_chordia/extractors/chordino.py
lv_chordia/extractors/cnn_features.py
lv_chordia/extractors/complex_chord_preprocess.py
lv_chordia/extractors/cqt.py
lv_chordia/extractors/ismir2017_chord_extractor.py
lv_chordia/extractors/jam_converter.py
lv_chordia/extractors/key_preprocess.py
lv_chordia/extractors/torch_helper.py
lv_chordia/extractors/wave_extractor.py
lv_chordia/extractors/xhmm_decoder.py
lv_chordia-1.0.0.dist-info/METADATA
lv_chordia-1.0.0.dist-info/WHEEL
lv_chordia-1.0.0.dist-info/entry_points.txt
lv_chordia-1.0.0.dist-info/licenses/LICENSE
lv_chordia-1.0.0.dist-info/RECORD
