Metadata-Version: 2.4
Name: lv-chordia
Version: 1.0.0
Summary: Large-Vocabulary Chord Transcription via Chord Structure Decomposition - ISMIR 2019
Project-URL: Homepage, https://github.com/music-x-lab/ISMIR2019-Large-Vocabulary-Chord-Recognition
Project-URL: Repository, https://github.com/music-x-lab/ISMIR2019-Large-Vocabulary-Chord-Recognition
Project-URL: Original Research, https://archives.ismir.net/ismir2019/paper/000078.pdf
Project-URL: Bug Reports, https://github.com/music-x-lab/ISMIR2019-Large-Vocabulary-Chord-Recognition/issues
Project-URL: Documentation, https://github.com/music-x-lab/ISMIR2019-Large-Vocabulary-Chord-Recognition#readme
Author: Junyan Jiang, Ke Chen, Wei Li, Gus Xia
Maintainer: Package Maintainers
License: MIT License
License-File: LICENSE
Keywords: audio,chord,chord-recognition,deep-learning,mir,music,music-information-retrieval,pytorch,recognition,transcription
Classifier: Development Status :: 4 - Beta
Classifier: Intended Audience :: Developers
Classifier: Intended Audience :: Science/Research
Classifier: License :: OSI Approved :: MIT License
Classifier: Operating System :: OS Independent
Classifier: Programming Language :: Python :: 3
Classifier: Programming Language :: Python :: 3.8
Classifier: Programming Language :: Python :: 3.9
Classifier: Programming Language :: Python :: 3.10
Classifier: Programming Language :: Python :: 3.11
Classifier: Programming Language :: Python :: 3.12
Classifier: Topic :: Multimedia :: Sound/Audio :: Analysis
Classifier: Topic :: Scientific/Engineering :: Artificial Intelligence
Classifier: Topic :: Software Development :: Libraries :: Python Modules
Requires-Python: >=3.8
Requires-Dist: figures>=0.3.16
Requires-Dist: h5py>=2.9.0
Requires-Dist: jams>=0.3.4
Requires-Dist: joblib>=0.13.2
Requires-Dist: librosa>=0.7.2
Requires-Dist: matplotlib>=2.2.4
Requires-Dist: mir-eval>=0.5
Requires-Dist: numpy>=1.19.2
Requires-Dist: pretty-midi>=0.2.9
Requires-Dist: pumpp>=0.5.0
Requires-Dist: pydub>=0.23.1
Requires-Dist: scikit-learn>=0.23.2
Requires-Dist: torch>=1.4.0
Provides-Extra: dev
Requires-Dist: black>=22.0; extra == 'dev'
Requires-Dist: build>=0.10.0; extra == 'dev'
Requires-Dist: flake8>=4.0; extra == 'dev'
Requires-Dist: pytest>=6.0; extra == 'dev'
Requires-Dist: twine>=4.0.0; extra == 'dev'
